gps/__init__.py
gps/aiogps.py
gps/client.py
gps/clienthelpers.py
gps/fake.py
gps/gps.py
gps/misc.py
gps/ubx.py
gps/watch_options.py
gpsd-3.27.5.0.1.data/data/share/gpsd/icons/gpsd-logo.png
gpsd-3.27.5.0.1.data/scripts/example_aiogps
gpsd-3.27.5.0.1.data/scripts/gegps
gpsd-3.27.5.0.1.data/scripts/gpsData
gpsd-3.27.5.0.1.data/scripts/gpscsv
gpsd-3.27.5.0.1.data/scripts/gpsplot
gpsd-3.27.5.0.1.data/scripts/gpsprof
gpsd-3.27.5.0.1.data/scripts/gpssim
gpsd-3.27.5.0.1.data/scripts/gpssubframe
gpsd-3.27.5.0.1.data/scripts/ntpshmviz
gpsd-3.27.5.0.1.data/scripts/skyview2svg
gpsd-3.27.5.0.1.data/scripts/ubxtool
gpsd-3.27.5.0.1.data/scripts/webgps
gpsd-3.27.5.0.1.data/scripts/xgps
gpsd-3.27.5.0.1.data/scripts/xgpsspeed
gpsd-3.27.5.0.1.data/scripts/zerk
gpsd-3.27.5.0.1.dist-info/licenses/AUTHORS
gpsd-3.27.5.0.1.dist-info/licenses/COPYING
gpsd-3.27.5.0.1.dist-info/licenses/LICENSE
gpsd-3.27.5.0.1.dist-info/METADATA
gpsd-3.27.5.0.1.dist-info/WHEEL
gpsd-3.27.5.0.1.dist-info/top_level.txt
gpsd-3.27.5.0.1.dist-info/RECORD
