Metadata-Version: 2.4
Name: gpsd
Version: 3.27.5.0.1
Summary: "fork of gps module from gpsd."
Home-page: https://gpsd.io/
Author: Eric S Raymond
Author-email: esr@thyrsus.com
Maintainer: James T Browning
Maintainer-email: JamesB.fe80@gmail.com
License: BSD 2-Clause License
Project-URL: Bug Tracker, https://gitlab.com/jamesb_fe80/gpsd/-/issues
Project-URL: IRC, https://web.libera.chat/
Project-URL: Project, https://gitlab.com/jamesb_fe80/gpsd
Project-URL: Support, https://gpsd.io/SUPPORT.html
Classifier: Programming Language :: Python :: 3
Classifier: Programming Language :: Python :: 2
Classifier: License :: OSI Approved :: BSD License
Classifier: Operating System :: POSIX
Classifier: Development Status :: 5 - Production/Stable
License-File: LICENSE
License-File: COPYING
License-File: AUTHORS
Dynamic: license-file
